LICENSE.txt
MANIFEST.in
README.md
setup.py
dprofiles/__init__.py
dprofiles/client.py
dprofiles/errors.py
dprofiles.egg-info/PKG-INFO
dprofiles.egg-info/SOURCES.txt
dprofiles.egg-info/dependency_links.txt
dprofiles.egg-info/requires.txt
dprofiles.egg-info/top_level.txt
dprofiles/ext/__init__.py
dprofiles/ext/base.py
dprofiles/ext/client.py
dprofiles/ext/exceptions.py
dprofiles/ext/http.py
dprofiles/ext/models/__init__.py
dprofiles/ext/models/guild.py
dprofiles/ext/models/user.py