Metadata-Version: 2.1
Name: dprofiles
Version: 0.0.2
Summary: Discord Oauth2 Client for Quart and a easy to use API Wrapper for dprofiles.xyz
Home-page: https://github.com/Titanic-official/dprofiles
Author: Titanic
Author-email: admin@dprofiles.xyz
License: MIT LICENSE
Keywords: discord,Oauth2,discordpy,discord py
Platform: UNKNOWN
Classifier: Development Status :: 4 - Beta
Classifier: Intended Audience :: Education
Classifier: Operating System :: Microsoft :: Windows :: Windows 10
Classifier: License :: OSI Approved :: MIT License
Classifier: Programming Language :: Python :: 3
